MANIFEST.in
README.rst
setup.py
django_jsonbfield.egg-info/PKG-INFO
django_jsonbfield.egg-info/SOURCES.txt
django_jsonbfield.egg-info/dependency_links.txt
django_jsonbfield.egg-info/requires.txt
django_jsonbfield.egg-info/top_level.txt
jsonbfield/__init__.py
jsonbfield/fields.py
jsonbfield/forms.py
jsonbfield/models.py
jsonbfield/tests.py