Metadata-Version: 1.1
Name: django-jsonbfield
Version: 0.1.0
Summary: Django JSONField that utilized PostGRESQL jsonb field type
Home-page: https://github.com/totalgood/django-jsonbfield/
Author: Tome Cvitan
Author-email: tome@cvitan.com
License: BSD
Keywords: django postgres jsonb
Platform: UNKNOWN
Classifier: Development Status :: 3 - Alpha
Classifier: Intended Audience :: Developers
Classifier: Topic :: Software Development :: Libraries
Classifier: License :: OSI Approved :: BSD License
Classifier: Programming Language :: Python :: 2.7
Classifier: Programming Language :: Python :: 3.3
Classifier: Programming Language :: Python :: 3.4
Classifier: Programming Language :: Python :: 3.5
